Example.ipynb
LICENSE.md
MANIFEST.in
README.rst
requirements.txt
setup.py
post_truth_checker/__init__.py
post_truth_checker/badsites.csv
post_truth_checker/baits.csv
post_truth_checker/detector_test.py
post_truth_checker/main.py
post_truth_checker/my_parser.py
post_truth_checker/opinionwords.csv
post_truth_checker/page.py
post_truth_checker/sources_loader.py
post_truth_checker.egg-info/PKG-INFO
post_truth_checker.egg-info/SOURCES.txt
post_truth_checker.egg-info/dependency_links.txt
post_truth_checker.egg-info/not-zip-safe
post_truth_checker.egg-info/requires.txt
post_truth_checker.egg-info/top_level.txt