Metadata-Version: 1.0
Name: post-truth-checker
Version: 0.2
Summary: Checks reliability of sites
Home-page: https://github.com/AGHPythonCourse2017/zad3-detori
Author: Wojciech Kubaty
Author-email: UNKNOWN
License: UNKNOWN
Platform: UNKNOWN
